Metadata-Version: 2.1
Name: opcua-for-dhbw
Version: 0.98.13
Summary: Pure Python OPC-UA client and server library edited for internal purposes of DHBW Mosbach (ctrlX AUTOMATION - OPC UA Server)
Home-page: http://freeopcua.github.io/
Author: Olivier Roulet-Dubonnet (Edited by Adrian)
Author-email: author@example.com
License: GNU Lesser General Public License v3 or later
Classifier: Programming Language :: Python
Classifier: Programming Language :: Python :: 3
Classifier: Programming Language :: Python :: 2
Classifier: Development Status :: 4 - Beta
Classifier: Intended Audience :: Developers
Classifier: Operating System :: OS Independent
Classifier: License :: OSI Approved :: GNU Lesser General Public License v3 or later (LGPLv3+)
Classifier: Topic :: Software Development :: Libraries :: Python Modules
Provides: opcua_for_dhbw
License-File: COPYING
Requires-Dist: lxml
Requires-Dist: python-dateutil
Requires-Dist: pytz
Requires-Dist: enum34 ; python_version < "3"
Requires-Dist: futures ; python_version < "3"
Requires-Dist: trollius ; python_version < "3"
Provides-Extra: encryption
Requires-Dist: cryptography ; extra == 'encryption'
